youtube_mcp/__init__.py
youtube_mcp/server.py
youtube_mcp/transcript.py
youtube_mcp/url.py
youtube_mcp/video_info.py
kzmshx_youtube_mcp-0.1.1.dist-info/METADATA
kzmshx_youtube_mcp-0.1.1.dist-info/WHEEL
kzmshx_youtube_mcp-0.1.1.dist-info/entry_points.txt
kzmshx_youtube_mcp-0.1.1.dist-info/licenses/LICENSE
kzmshx_youtube_mcp-0.1.1.dist-info/RECORD
