Metadata-Version: 2.4
Name: kzmshx-youtube-mcp
Version: 0.1.1
Summary: MCP server for extracting YouTube video transcripts and metadata
Project-URL: Homepage, https://github.com/kzmshx/youtube-mcp
Project-URL: Repository, https://github.com/kzmshx/youtube-mcp
Author: kzmshx
License: MIT License
License-File: LICENSE
Requires-Python: >=3.11
Requires-Dist: fastmcp<3.0.0,>=2.14.0
Requires-Dist: youtube-transcript-api<2.0.0,>=1.0.0
Requires-Dist: yt-dlp>=2024.0.0
